aughra/__init__.py
aughra-0.0.1.dist-info/LICENSE
aughra-0.0.1.dist-info/METADATA
aughra-0.0.1.dist-info/WHEEL
aughra-0.0.1.dist-info/top_level.txt
aughra-0.0.1.dist-info/RECORD
