Metadata-Version: 2.1
Name: aughra
Version: 0.0.1
Summary: Catalog Server and Algorithm Repository
Home-page: https://www.frootlab.org/aughra
Author: Frootlab Developers
Author-email: contact@frootlab.org
License: GPLv3
Keywords: catalog catalog-software
Platform: UNKNOWN
Classifier: Development Status :: 1 - Planning
Classifier: Intended Audience :: Developers
Classifier: Intended Audience :: Science/Research
Classifier: License :: OSI Approved :: GNU General Public License v3 (GPLv3)
Classifier: Programming Language :: Python :: 3
Classifier: Programming Language :: Python :: 3.7
Classifier: Operating System :: OS Independent
Classifier: Topic :: Internet :: WWW/HTTP :: Dynamic Content
Classifier: Topic :: Software Development :: Libraries :: Python Modules
Requires-Python: >=3.7
Requires-Dist: numpy (>=1.15)
Requires-Dist: hup (>=0.9.2)
